sql_scan/__init__.py
sql_scan/file_writer.py
sql_scan/formatter.py
sql_scan/name_cleaner.py
sql_scan/table_extractor.py
sql_scan/where_extractor.py
sql_scan-0.5.dist-info/LICENSE
sql_scan-0.5.dist-info/METADATA
sql_scan-0.5.dist-info/WHEEL
sql_scan-0.5.dist-info/entry_points.txt
sql_scan-0.5.dist-info/top_level.txt
sql_scan-0.5.dist-info/RECORD
